pyfoobar/__about__.py
pyfoobar/__init__.py
pyfoobar/cli.py
pyfoobar/main.py
texdown-0.0.6.dist-info/LICENSE
texdown-0.0.6.dist-info/METADATA
texdown-0.0.6.dist-info/WHEEL
texdown-0.0.6.dist-info/entry_points.txt
texdown-0.0.6.dist-info/top_level.txt
texdown-0.0.6.dist-info/RECORD
